rlssm/__init__.py
rlssm/fits.py
rlssm/fits_DDM.py
rlssm/fits_RL.py
rlssm/fits_race.py
rlssm/load_data.py
rlssm/models.py
rlssm/models_ALBA.py
rlssm/models_ARDM.py
rlssm/models_DDM.py
rlssm/models_LBA.py
rlssm/models_RDM.py
rlssm/models_RL.py
rlssm/plotting.py
rlssm/random.py
rlssm/stan_utility.py
rlssm/utils.py
rlssm/version.py
rlssm/stan_models/ALBA_2A.stan
rlssm/stan_models/ARDM_2A.stan
rlssm/stan_models/DDM.stan
rlssm/stan_models/DDM_bias.stan
rlssm/stan_models/DDM_bias_driftvar_spvar.stan
rlssm/stan_models/DDM_bias_driftvar_spvar_beta.stan
rlssm/stan_models/DDM_bias_driftvar_spvar_corr.stan
rlssm/stan_models/DDM_bias_driftvar_spvar_corr_beta.stan
rlssm/stan_models/DDM_bias_spvar.stan
rlssm/stan_models/DDM_driftvar.stan
rlssm/stan_models/DDM_driftvar_spvar.stan
rlssm/stan_models/DDM_spvar.stan
rlssm/stan_models/LBA_2A.stan
rlssm/stan_models/RDM_2A.stan
rlssm/stan_models/RLALBA_2A.stan
rlssm/stan_models/RLALBA_2A_2lr.stan
rlssm/stan_models/RLARDM_2A.stan
rlssm/stan_models/RLARDM_2A_2lr.stan
rlssm/stan_models/RLDDM.stan
rlssm/stan_models/RLDDM_2lr.stan
rlssm/stan_models/RLDDM_2lr_thrmod.stan
rlssm/stan_models/RLDDM_nonlin.stan
rlssm/stan_models/RLDDM_nonlin_2lr.stan
rlssm/stan_models/RLDDM_nonlin_2lr_thrmod.stan
rlssm/stan_models/RLDDM_nonlin_thrmod.stan
rlssm/stan_models/RLDDM_thrmod.stan
rlssm/stan_models/RLLBA_2A.stan
rlssm/stan_models/RLLBA_2A_2lr.stan
rlssm/stan_models/RLLBA_2A_2lr_nonlin.stan
rlssm/stan_models/RLLBA_2A_nonlin.stan
rlssm/stan_models/RLRDM_2A.stan
rlssm/stan_models/RLRDM_2A_2lr.stan
rlssm/stan_models/RLRDM_2A_2lr_nonlin.stan
rlssm/stan_models/RLRDM_2A_nonlin.stan
rlssm/stan_models/RL_2A.stan
rlssm/stan_models/RL_2A_2lr.stan
rlssm/stan_models/RL_2A_pow.stan
rlssm/stan_models/RL_2A_pow_2lr.stan
rlssm/stan_models/hierALBA_2A.stan
rlssm/stan_models/hierARDM_2A.stan
rlssm/stan_models/hierDDM.stan
rlssm/stan_models/hierDDM_bias.stan
rlssm/stan_models/hierDDM_cond.stan
rlssm/stan_models/hierDDM_driftvar.stan
rlssm/stan_models/hierLBA_2A.stan
rlssm-0.1.1.dev0.dist-info/LICENSE
rlssm-0.1.1.dev0.dist-info/METADATA
rlssm-0.1.1.dev0.dist-info/WHEEL
rlssm-0.1.1.dev0.dist-info/top_level.txt
rlssm-0.1.1.dev0.dist-info/RECORD
