Metadata-Version: 1.2
Name: rlssm
Version: 0.1.1.dev0
Summary: rlssm: a package for fitting RL models, SSM, and combinations of the two
Home-page: https://github.com/laurafontanesi/rlssm
Author: Laura Fontanesi
Author-email: laura.fontanesi.1@gmail.com
Maintainer: Laura Fontanesi
Maintainer-email: laura.fontanesi.1@gmail.com
License: MIT
Platform: OS Independent
Classifier: Development Status :: 1 - Planning
Classifier: Environment :: Console
Classifier: Intended Audience :: Science/Research
Classifier: License :: OSI Approved :: MIT License
Classifier: Operating System :: OS Independent
Classifier: Programming Language :: Python
Classifier: Topic :: Scientific/Engineering
Requires: numpy
Requires: pandas
Requires: pystan
